[
  {
    "seed": 314,
    "N": 200,
    "window": 2,
    "step": 700,
    "prev_k": 0,
    "new_k": 4,
    "margin": 0.1246,
    "threshold": 0.01,
    "j3": -0.2864,
    "j4": -0.1618,
    "h3": 0.7806,
    "h4": 0.9796
  },
  {
    "seed": 314,
    "N": 200,
    "window": 13,
    "step": 2900,
    "prev_k": 4,
    "new_k": 1,
    "margin": 0.0,
    "threshold": 0.01,
    "j3": 0.5379,
    "j4": 0.5379,
    "h3": 1.419,
    "h4": 1.419
  },
  {
    "seed": 314,
    "N": 200,
    "window": 14,
    "step": 3100,
    "prev_k": 1,
    "new_k": 4,
    "margin": 0.0021,
    "threshold": 0.01,
    "j3": 0.7016,
    "j4": 0.7037,
    "h3": 1.4466,
    "h4": 1.6688
  }
]