[
  {
    "seed": 7,
    "N": 200,
    "window": 2,
    "step": 700,
    "prev_k": 0,
    "new_k": 4,
    "margin": 0.0215,
    "threshold": 0.01,
    "j3": -0.3185,
    "j4": -0.297,
    "h3": 0.273,
    "h4": 0.273
  },
  {
    "seed": 7,
    "N": 200,
    "window": 5,
    "step": 1300,
    "prev_k": 4,
    "new_k": 1,
    "margin": 0.0,
    "threshold": 0.01,
    "j3": 0.1781,
    "j4": 0.1781,
    "h3": 0.8659,
    "h4": 0.8659
  },
  {
    "seed": 7,
    "N": 200,
    "window": 6,
    "step": 1500,
    "prev_k": 1,
    "new_k": 2,
    "margin": 0.0,
    "threshold": 0.01,
    "j3": 0.5067,
    "j4": 0.5067,
    "h3": 1.0409,
    "h4": 1.0409
  },
  {
    "seed": 7,
    "N": 200,
    "window": 8,
    "step": 1900,
    "prev_k": 2,
    "new_k": 3,
    "margin": 0.0,
    "threshold": 0.01,
    "j3": 0.8067,
    "j4": 0.8067,
    "h3": 1.4299,
    "h4": 1.4299
  },
  {
    "seed": 7,
    "N": 200,
    "window": 9,
    "step": 2100,
    "prev_k": 3,
    "new_k": 4,
    "margin": 0.2636,
    "threshold": 0.01,
    "j3": 0.4827,
    "j4": 0.7463,
    "h3": 0.971,
    "h4": 1.361
  }
]