{
  "point_id": "P3",
  "p_link_birth": 0.01,
  "bg_inject": 0.003,
  "seed": 314,
  "quiet_steps": 5000,
  "eta_ratio": 1.5241,
  "collapse_flag": false,
  "cycles_total": 261,
  "cycles_per_1k": 52.2,
  "time_to_first_cycle": 439,
  "opp_per_1k": 32.4,
  "min_links": 164,
  "s03": 34,
  "max_s": 0.7097,
  "spr": 0.1211,
  "compress": 0.3515,
  "X": 0.9946,
  "R": 0,
  "C": 0.3515,
  "B": 0.1211,
  "strong_cov": 0.3727,
  "miss_strong": 0.613,
  "miss_energy": 0.229,
  "miss_state": 0.061,
  "miss_sync": 0.097,
  "elapsed": 25.1
}