{
  "seed": 789,
  "variance": 0.0,
  "cycles": 234,
  "cycles_per_1k": 46.8,
  "cycle_type_count": 2,
  "cycle_type_entropy": 0.9788,
  "top1_share": 0.5855,
  "syn_count": 136,
  "auto_count": 45,
  "mean_island": 1.72,
  "max_island": 4,
  "coexistence_rate": 0.56,
  "island_births_per_1k": 8.6,
  "island_deaths_per_1k": 8.4,
  "mean_turnover": 0,
  "boundary_crossing_per_1k": 0.0,
  "rigidity_index": 1.0,
  "fert_corr_syn": 0,
  "fert_corr_auto": 0,
  "spr": 0.1241,
  "X": 0.4801,
  "min_links": 187,
  "runaway": false,
  "elapsed": 28.9
}